[
  {
    "msgId": 19846375,
    "dateLocale": "09:48:41 PM",
    "msgChannel": "MirrorBridge"
  },
  {
    "msgId": 19846376,
    "text": "Is there any one who got the losss please send me the screen shot",
    "dateLocale": "09:49:26 PM",
    "msgChannel": "MirrorBridge"
  },
  {
    "msgId": 19846377,
    "text": "hello",
    "dateLocale": "12:26:12 PM",
    "msgChannel": "MirrorBridge"
  },
  {
    "msgId": 19846378,
    "text": "Is there any one who got the losss please send me the screen shotIs there any one who got the losss please send me the screen shotIs there any one who got the losss please send me the screen shotIs there any one who got the losss please send me the screen shot",
    "dateLocale": "12:26:23 PM",
    "msgChannel": "MirrorBridge"
  },
  {
    "msgId": 19846379,
    "text": "Is there any one who got the losss please send me the screen shot",
    "dateLocale": "12:26:23 PM",
    "msgChannel": "MirrorBridge"
  }
]